jsuniv_sllib/__init__.py
jsuniv_sllib/test.py
jsuniv_sllib/classification/__init__.py
jsuniv_sllib/classification/app.py
jsuniv_sllib/classification/config.py
jsuniv_sllib/classification/dataset.py
jsuniv_sllib/classification/evalution.py
jsuniv_sllib/classification/predict.py
jsuniv_sllib/classification/split_dataset.py
jsuniv_sllib/classification/test.py
jsuniv_sllib/classification/train.py
jsuniv_sllib/classification/utils.py
jsuniv_sllib/classification/visual_model.py
jsuniv_sllib/classification/models/AlexNet.py
jsuniv_sllib/classification/models/DenseNet.py
jsuniv_sllib/classification/models/GoogleNet.py
jsuniv_sllib/classification/models/LeNet.py
jsuniv_sllib/classification/models/ResNet.py
jsuniv_sllib/classification/models/SeNet.py
jsuniv_sllib/classification/models/VggNet.py
jsuniv_sllib/classification/models/__init__.py
jsuniv_sllib/detection/__init__.py
jsuniv_sllib/segementation/__init__.py
major_s/__init__.py
major_s/test.py
major_s/classification/__init__.py
major_s/classification/app.py
major_s/classification/config.py
major_s/classification/dataset.py
major_s/classification/evalution.py
major_s/classification/predict.py
major_s/classification/split_dataset.py
major_s/classification/test.py
major_s/classification/train.py
major_s/classification/utils.py
major_s/classification/visual_model.py
major_s/classification/models/AlexNet.py
major_s/classification/models/DenseNet.py
major_s/classification/models/GoogleNet.py
major_s/classification/models/LeNet.py
major_s/classification/models/ResNet.py
major_s/classification/models/SeNet.py
major_s/classification/models/VggNet.py
major_s/classification/models/__init__.py
major_s/detection/__init__.py
major_s/detection/models/__init__.py
major_s/segementation/__init__.py
major_s/segementation/config.py
major_s/segementation/dataset.py
major_s/segementation/evalution.py
major_s/segementation/predict.py
major_s/segementation/split_dataset.py
major_s-0.3.dist-info/METADATA
major_s-0.3.dist-info/RECORD
major_s-0.3.dist-info/WHEEL
major_s-0.3.dist-info/top_level.txt
