Metadata-Version: 2.1
Name: major-s
Version: 0.3
Summary: AIAgorithmPack
Home-page: https://github.com/Major357/major_s
Author: major_s
Author-email: 1171657161@qq.com
License: UNKNOWN
Platform: UNKNOWN
